ovalbee/__init__.py
ovalbee-0.0.2.dist-info/METADATA
ovalbee-0.0.2.dist-info/WHEEL
ovalbee-0.0.2.dist-info/top_level.txt
ovalbee-0.0.2.dist-info/RECORD
