Metadata-Version: 2.4
Name: ovalbee
Version: 0.0.2
Summary: Ovalbee python SDK
Author-email: Ovalbee <support@ovalbee.com>
Requires-Python: >=3.10
